azurefunctions/extensions/http/fastapi/__init__.py
azurefunctions/extensions/http/fastapi/web.py
azurefunctions_extensions_http_fastapi-1.0.0.dist-info/licenses/LICENSE
samples/fastapi_samples_streaming_download/function_app.py
samples/fastapi_samples_streaming_upload/function_app.py
azurefunctions_extensions_http_fastapi-1.0.0.dist-info/METADATA
azurefunctions_extensions_http_fastapi-1.0.0.dist-info/WHEEL
azurefunctions_extensions_http_fastapi-1.0.0.dist-info/top_level.txt
azurefunctions_extensions_http_fastapi-1.0.0.dist-info/RECORD
